odoo10_addon_purchase_order_line_sequence-10.0.1.0.1-nspkg.pth
odoo/addons/purchase_order_line_sequence/README.rst
odoo/addons/purchase_order_line_sequence/__init__.py
odoo/addons/purchase_order_line_sequence/__manifest__.py
odoo/addons/purchase_order_line_sequence/hooks.py
odoo/addons/purchase_order_line_sequence/i18n/fr.po
odoo/addons/purchase_order_line_sequence/i18n/purchase_order_line_sequence.pot
odoo/addons/purchase_order_line_sequence/models/__init__.py
odoo/addons/purchase_order_line_sequence/models/invoice.py
odoo/addons/purchase_order_line_sequence/models/purchase.py
odoo/addons/purchase_order_line_sequence/static/description/icon.png
odoo/addons/purchase_order_line_sequence/tests/__init__.py
odoo/addons/purchase_order_line_sequence/tests/test_po_lines_sequence.py
odoo/addons/purchase_order_line_sequence/views/purchase_view.xml
odoo/addons/purchase_order_line_sequence/views/report_purchaseorder.xml
odoo/addons/purchase_order_line_sequence/views/report_purchasequotation.xml
odoo10_addon_purchase_order_line_sequence-10.0.1.0.1.dist-info/METADATA
odoo10_addon_purchase_order_line_sequence-10.0.1.0.1.dist-info/WHEEL
odoo10_addon_purchase_order_line_sequence-10.0.1.0.1.dist-info/namespace_packages.txt
odoo10_addon_purchase_order_line_sequence-10.0.1.0.1.dist-info/top_level.txt
odoo10_addon_purchase_order_line_sequence-10.0.1.0.1.dist-info/RECORD
