Metadata-Version: 2.1
Name: odoo10-addon-purchase-order-line-sequence
Version: 10.0.1.0.1
Summary: Adds sequence to PO lines and propagates it toInvoice lines and Stock Moves
Home-page: http://www.camptocamp.com
Author: Camptocamp, Eficent, Serpent CS, Odoo Community Association (OCA)
Author-email: support@odoo-community.org
License: AGPL-3
Platform: UNKNOWN
Classifier: Programming Language :: Python
Classifier: Framework :: Odoo
Classifier: License :: OSI Approved :: GNU Affero General Public License v3
Requires-Python: ~=2.7
Requires-Dist: odoo10-addon-stock-picking-line-sequence
Requires-Dist: odoo (<10.1dev,>=10.0)
